ml/__init__.py
ml/decision_tree.py
ml/kmeans.py
ml/knearest.py
ml/linear_regression.py
ml/logistic_regression.py
ml/neural_network.py
basic_ml-1.0.0.dist-info/LICENSE
basic_ml-1.0.0.dist-info/METADATA
basic_ml-1.0.0.dist-info/WHEEL
basic_ml-1.0.0.dist-info/top_level.txt
basic_ml-1.0.0.dist-info/RECORD
