Metadata-Version: 2.1
Name: basic-ml
Version: 1.0.0
Summary: A lightweight package for basic machine learning needs
Home-page: https://github.com/alankbi/basic-ml
Author: Alan Bi
Author-email: alan.bi326@gmail.com
License: UNKNOWN
Platform: UNKNOWN
Classifier: Programming Language :: Python :: 3
Classifier: License :: OSI Approved :: MIT License
Classifier: Operating System :: OS Independent
Requires-Python: >=3.6
